[{
    "title":"Java",
    "author":"Murthy",
    "category":"Programming Language",
    "price":800
},
    {
    "title":"Python",
    "author":"A.L.Thomus",
    "category":"Programming Language",
    "price":980
    },
    {
    "title":"Big Data",
    "author":"Reshma Banu",
    "category":"Technology",
    "price":1000
    },
    {
    "title":"Java Scripting",
    "author":"Vijayalakshmi",
    "category":"Scripting Language",
    "price":880
    },
    {
    "title":"Data Structure",
    "author":"Sowmya Dath",
    "category":"Technology",
    "price":790
    }
]